validataclass/__init__.py
validataclass/_version.py
validataclass/py.typed
validataclass/dataclasses/__init__.py
validataclass/dataclasses/defaults.py
validataclass/dataclasses/validataclass.py
validataclass/dataclasses/validataclass_field.py
validataclass/dataclasses/validataclass_mixin.py
validataclass/exceptions/__init__.py
validataclass/exceptions/base_exceptions.py
validataclass/exceptions/common_exceptions.py
validataclass/exceptions/dataclass_exceptions.py
validataclass/exceptions/datetime_exceptions.py
validataclass/exceptions/dict_exceptions.py
validataclass/exceptions/email_exceptions.py
validataclass/exceptions/list_exceptions.py
validataclass/exceptions/meta_exceptions.py
validataclass/exceptions/misc_exceptions.py
validataclass/exceptions/number_exceptions.py
validataclass/exceptions/regex_exceptions.py
validataclass/exceptions/string_exceptions.py
validataclass/exceptions/url_exceptions.py
validataclass/helpers/__init__.py
validataclass/helpers/dataclass_defaults.py
validataclass/helpers/dataclass_mixins.py
validataclass/helpers/dataclasses.py
validataclass/helpers/datetime_range.py
validataclass/helpers/unset_value.py
validataclass/internal/__init__.py
validataclass/internal/internet_helpers.py
validataclass/validators/__init__.py
validataclass/validators/allow_empty_string.py
validataclass/validators/any_of_validator.py
validataclass/validators/anything_validator.py
validataclass/validators/big_integer_validator.py
validataclass/validators/boolean_validator.py
validataclass/validators/dataclass_validator.py
validataclass/validators/date_validator.py
validataclass/validators/datetime_validator.py
validataclass/validators/decimal_validator.py
validataclass/validators/dict_validator.py
validataclass/validators/discard_validator.py
validataclass/validators/email_validator.py
validataclass/validators/enum_validator.py
validataclass/validators/float_to_decimal_validator.py
validataclass/validators/float_validator.py
validataclass-0.11.0.dist-info/LICENSE
validataclass-0.11.0.dist-info/METADATA
validataclass-0.11.0.dist-info/WHEEL
validataclass-0.11.0.dist-info/top_level.txt
validataclass-0.11.0.dist-info/RECORD
