Metadata-Version: 2.1
Name: validataclass
Version: 0.11.0
Summary: Library for input validation designed for (but not restricted to) JSON-based APIs, neatly integrating with dataclasses.
Home-page: https://github.com/binary-butterfly/validataclass
Author: binary butterfly GmbH
Author-email: lexi.stelter@binary-butterfly.de
License: MIT
Project-URL: Documentation, https://github.com/binary-butterfly/validataclass/blob/main/docs/index.md
Project-URL: Changelog, https://github.com/binary-butterfly/validataclass/blob/main/CHANGELOG.md
Project-URL: Issue Tracker, https://github.com/binary-butterfly/validataclass/issues
Classifier: Development Status :: 4 - Beta
Classifier: Intended Audience :: Developers
Classifier: License :: OSI Approved :: MIT License
Classifier: Operating System :: OS Independent
Classifier: Programming Language :: Python :: 3
Classifier: Programming Language :: Python :: 3.8
Classifier: Programming Language :: Python :: 3.9
Classifier: Programming Language :: Python :: 3.10
Classifier: Programming Language :: Python :: 3.11
Classifier: Programming Language :: Python :: 3.12
Classifier: Programming Language :: Python :: Implementation :: CPython
Classifier: Topic :: Software Development :: Libraries :: Python Modules
Classifier: Topic :: Utilities
Requires-Python: >=3.8
License-File: LICENSE
Requires-Dist: typing-extensions~=4.3
Provides-Extra: testing
Requires-Dist: pytest~=7.2; extra == "testing"
Requires-Dist: pytest-cov; extra == "testing"
Requires-Dist: coverage~=6.5; extra == "testing"
Requires-Dist: coverage-conditional-plugin~=0.5; extra == "testing"
Requires-Dist: flake8~=7.0; extra == "testing"
Requires-Dist: mypy~=1.9; extra == "testing"
Requires-Dist: python-dateutil; extra == "testing"
Requires-Dist: types-python-dateutil; extra == "testing"
